<?xml version="1.0" encoding="utf-8" ?>
<dwsync>
<file name="angel_smile.gif" server="66.147.244.197//public_html/" local="129482168926173210" remote="129501230400000000" />
<file name="angry_smile.gif" server="66.147.244.197//public_html/" local="129482168925873192" remote="129501230400000000" />
<file name="broken_heart.gif" server="66.147.244.197//public_html/" local="129482168925593176" remote="129501230400000000" />
<file name="cake.gif" server="66.147.244.197//public_html/" local="129482168924673124" remote="129501230400000000" />
<file name="confused_smile.gif" server="66.147.244.197//public_html/" local="129482168922613006" remote="129501230400000000" />
<file name="cry_smile.gif" server="66.147.244.197//public_html/" local="129482168922032973" remote="129501230400000000" />
<file name="devil_smile.gif" server="66.147.244.197//public_html/" local="129482168921412937" remote="129501230400000000" />
<file name="embaressed_smile.gif" server="66.147.244.197//public_html/" local="129482168918972798" remote="129501230400000000" />
<file name="envelope.gif" server="66.147.244.197//public_html/" local="129482168918262757" remote="129501230400000000" />
<file name="heart.gif" server="66.147.244.197//public_html/" local="129482168920802902" remote="129501230400000000" />
<file name="kiss.gif" server="66.147.244.197//public_html/" local="129482168917702725" remote="129501230400000000" />
<file name="lightbulb.gif" server="66.147.244.197//public_html/" local="129482168915752614" remote="129501230400000000" />
<file name="omg_smile.gif" server="66.147.244.197//public_html/" local="129482168915052573" remote="129501230400000000" />
<file name="regular_smile.gif" server="66.147.244.197//public_html/" local="129482168914342533" remote="129501230400000000" />
<file name="sad_smile.gif" server="66.147.244.197//public_html/" local="129482168912492427" remote="129501230400000000" />
<file name="shades_smile.gif" server="66.147.244.197//public_html/" local="129482168911692381" remote="129501230400000000" />
<file name="teeth_smile.gif" server="66.147.244.197//public_html/" local="129482168910722326" remote="129501230400000000" />
<file name="thumbs_down.gif" server="66.147.244.197//public_html/" local="129482168909292244" remote="129501230400000000" />
<file name="thumbs_up.gif" server="66.147.244.197//public_html/" local="129482168908202182" remote="129501230400000000" />
<file name="tounge_smile.gif" server="66.147.244.197//public_html/" local="129482168907322131" remote="129501230400000000" />
<file name="whatchutalkingabout_smile.gif" server="66.147.244.197//public_html/" local="129482168905842047" remote="129501230400000000" />
<file name="wink_smile.gif" server="66.147.244.197//public_html/" local="129482168904561973" remote="129501230400000000" />
</dwsync>